murraytait_cdktf/__init__.py
murraytait_cdktf/accounts.py
murraytait_cdktf/config.py
murraytait_cdktf/env.py
murraytait_cdktf/provider_factory.py
murraytait_cdktf/shared.py
murraytait_cdktf/tests/__init__.py
murraytait_cdktf/tests/conftest.py
murraytait_cdktf/tests/list_accounts_response.json
murraytait_cdktf/tests/test_accounts.py
murraytait_cdktf/tests/test_terraform.py
murraytait_cdktf/waf.py
murraytait_cdktf/web.py
murraytait_cdktf-0.5.5.dist-info/WHEEL
murraytait_cdktf-0.5.5.dist-info/METADATA
murraytait_cdktf-0.5.5.dist-info/RECORD
