Metadata-Version: 2.1
Name: murraytait-cdktf
Version: 0.5.5
Summary: 
Author: Murray Tait
Author-email: 6074789+deathtumble@users.noreply.github.com
Requires-Python: >=3.8,<4.0
Classifier: Programming Language :: Python :: 3
Classifier: Programming Language :: Python :: 3.10
Classifier: Programming Language :: Python :: 3.8
Classifier: Programming Language :: Python :: 3.9
Requires-Dist: boto3 (>=1.20.31,<2.0.0)
Requires-Dist: cdktf (>=0.9.2,<0.10.0)
Requires-Dist: cdktf-cdktf-provider-aws (>=5.0.26,<6.0.0)
Requires-Dist: constructs (>=10.0.29,<11.0.0)
